odoo/addons/currency_old_rate_notify/README.rst
odoo/addons/currency_old_rate_notify/__init__.py
odoo/addons/currency_old_rate_notify/__manifest__.py
odoo/addons/currency_old_rate_notify/data/ir_config_parameter.xml
odoo/addons/currency_old_rate_notify/data/ir_cron.xml
odoo/addons/currency_old_rate_notify/i18n/currency_old_rate_notify.pot
odoo/addons/currency_old_rate_notify/i18n/es.po
odoo/addons/currency_old_rate_notify/i18n/fr.po
odoo/addons/currency_old_rate_notify/i18n/it.po
odoo/addons/currency_old_rate_notify/models/__init__.py
odoo/addons/currency_old_rate_notify/models/res_currency_rate.py
odoo/addons/currency_old_rate_notify/readme/CONFIGURE.md
odoo/addons/currency_old_rate_notify/readme/CONTRIBUTORS.md
odoo/addons/currency_old_rate_notify/readme/DESCRIPTION.md
odoo/addons/currency_old_rate_notify/static/description/icon.png
odoo/addons/currency_old_rate_notify/static/description/index.html
odoo/addons/currency_old_rate_notify/static/description/notify_old_rates.png
odoo/addons/currency_old_rate_notify/tests/__init__.py
odoo/addons/currency_old_rate_notify/tests/test_old_rate_notify.py
odoo/addons/currency_old_rate_notify/wizards/__init__.py
odoo/addons/currency_old_rate_notify/wizards/res_config_settings.py
odoo/addons/currency_old_rate_notify/wizards/res_config_settings.xml
odoo_addon_currency_old_rate_notify-18.0.1.0.0.3.dist-info/METADATA
odoo_addon_currency_old_rate_notify-18.0.1.0.0.3.dist-info/WHEEL
odoo_addon_currency_old_rate_notify-18.0.1.0.0.3.dist-info/top_level.txt
odoo_addon_currency_old_rate_notify-18.0.1.0.0.3.dist-info/RECORD
